LICENSE
MANIFEST.in
NOTICE
README.md
setup.py
lib/emq/__init__.py
lib/emq/client/__init__.py
lib/emq/client/clientfactory.py
lib/emq/client/constants.py
lib/emq/client/requestchecker.py
lib/emq/client/thttpclient.py
lib/emq/common/EMQBaseService.py
lib/emq/common/__init__.py
lib/emq/common/constants.py
lib/emq/common/ttypes.py
lib/emq/message/MessageService.py
lib/emq/message/__init__.py
lib/emq/message/constants.py
lib/emq/message/ttypes.py
lib/emq/queue/QueueService.py
lib/emq/queue/__init__.py
lib/emq/queue/constants.py
lib/emq/queue/ttypes.py
lib/emq/range/__init__.py
lib/emq/range/constants.py
lib/emq/range/ttypes.py
lib/emq/statistics/StatisticsService.py
lib/emq/statistics/__init__.py
lib/emq/statistics/constants.py
lib/emq/statistics/ttypes.py
lib/emr/__init__.py
lib/emr/client/__init__.py
lib/emr/client/clientfactory.py
lib/emr/client/constants.py
lib/emr/client/emrthttpclient.py
lib/emr/exceptions/GalaxyEmrServiceException.py
lib/emr/exceptions/__init__.py
lib/emr/service/EMRMasterService.py
lib/emr/service/EMRSchedulerService.py
lib/emr/service/__init__.py
lib/emr/service/constants.py
lib/emr/service/ttypes.py
lib/galaxy/__init__.py
lib/galaxy/common/__init__.py
lib/galaxy/common/clientfactory.py
lib/galaxy/common/configs.py
lib/galaxy/common/httpclient.py
lib/galaxy/common/utils.py
lib/galaxy_sdk_python.egg-info/PKG-INFO
lib/galaxy_sdk_python.egg-info/SOURCES.txt
lib/galaxy_sdk_python.egg-info/dependency_links.txt
lib/galaxy_sdk_python.egg-info/top_level.txt
lib/rpc/__init__.py
lib/rpc/auth/AuthService.py
lib/rpc/auth/__init__.py
lib/rpc/auth/constants.py
lib/rpc/auth/ttypes.py
lib/rpc/authorization/__init__.py
lib/rpc/authorization/constants.py
lib/rpc/authorization/ttypes.py
lib/rpc/common/BaseService.py
lib/rpc/common/__init__.py
lib/rpc/common/constants.py
lib/rpc/common/ttypes.py
lib/rpc/errors/__init__.py
lib/rpc/errors/constants.py
lib/rpc/errors/ttypes.py
lib/sds/__init__.py
lib/sds/admin/AdminService.py
lib/sds/admin/__init__.py
lib/sds/admin/constants.py
lib/sds/admin/ttypes.py
lib/sds/auth/AuthService.py
lib/sds/auth/__init__.py
lib/sds/auth/constants.py
lib/sds/auth/ttypes.py
lib/sds/client/__init__.py
