Metadata-Version: 1.1
Name: galaxy-sdk-python
Version: 1.2.7
Summary: Xiaomi Galaxy SDK for Python
Home-page: http://dev.mi.com
Author: Xiaomi Technology Co.
Author-email: heliangliang@xiaomi.com
License: Apache License (2.0)
Platform: UNKNOWN
Classifier: Development Status :: 4 - Beta
Classifier: Topic :: Software Development :: Libraries
Classifier: License :: OSI Approved :: Apache Software License
Classifier: Intended Audience :: Developers
